{"stats":{"minecraft:mined":{"minecraft:lever":1,"minecraft:player_head":1,"minecraft:redstone_wall_torch":1},"minecraft:custom":{"minecraft:inspect_dropper":185,"minecraft:mob_kills":63,"minecraft:interact_with_anvil":5,"minecraft:inspect_hopper":274,"minecraft:open_barrel":2,"minecraft:damage_dealt_resisted":30,"minecraft:leave_game":10,"minecraft:time_since_death":377704,"minecraft:climb_one_cm":21607,"minecraft:damage_resisted":2571,"minecraft:sprint_one_cm":526944,"minecraft:walk_one_cm":1964198,"minecraft:drop":321,"minecraft:deaths":43,"minecraft:sneak_time":140497,"minecraft:walk_under_water_one_cm":128201,"minecraft:boat_one_cm":3830,"minecraft:interact_with_lectern":6,"minecraft:jump":8894,"minecraft:walk_on_water_one_cm":74936,"minecraft:tune_noteblock":46,"minecraft:play_one_minute":3688076,"minecraft:time_since_rest":377705,"minecraft:damage_taken":7539,"minecraft:damage_dealt":7665,"minecraft:swim_one_cm":19581,"minecraft:fly_one_cm":18641914,"minecraft:open_chest":155,"minecraft:crouch_one_cm":287195,"minecraft:aviate_one_cm":519081,"minecraft:fall_one_cm":32083,"minecraft:inspect_dispenser":21},"minecraft:dropped":{"minecraft:stripped_spruce_log":1,"minecraft:porkchop":371,"minecraft:barrier":3,"minecraft:cobblestone":2,"minecraft:command_block":9,"minecraft:polished_blackstone_button":1,"minecraft:grass_block":1,"minecraft:cobblestone_stairs":1,"minecraft:end_rod":1,"minecraft:spruce_leaves":3,"minecraft:diorite":3,"minecraft:smooth_quartz":2,"minecraft:repeater":16,"minecraft:mutton":170,"minecraft:wooden_axe":3,"minecraft:white_concrete":1,"minecraft:zombie_horse_spawn_egg":3,"minecraft:writable_book":2,"minecraft:sand":6,"minecraft:black_concrete":4,"minecraft:armor_stand":1,"minecraft:redstone":7,"minecraft:farmland":7,"minecraft:player_head":10,"minecraft:yellow_wool":2,"minecraft:chicken":196,"minecraft:comparator":1,"minecraft:stone_slab":2,"minecraft:filled_map":3,"minecraft:hay_block":3,"minecraft:stone":5,"minecraft:dropper":1,"minecraft:hopper":9,"minecraft:redstone_torch":4,"minecraft:birch_sign":1,"minecraft:beef":234,"minecraft:written_book":3,"minecraft:lectern":5},"minecraft:killed_by":{"minecraft:stray":12,"minecraft:vindicator":4},"minecraft:used":{"minecraft:light_blue_banner":9,"minecraft:netherite_sword":40,"minecraft:writable_book":1,"minecraft:armor_stand":18,"minecraft:polished_blackstone":1,"minecraft:dispenser":8,"minecraft:redstone":336,"minecraft:ladder":4,"minecraft:oak_sign":2,"minecraft:chest":17,"minecraft:stone":740,"minecraft:debug_stick":55,"minecraft:spruce_leaves":2,"minecraft:stripped_birch_wood":4,"minecraft:grass":4,"minecraft:player_head":19,"minecraft:farmland":30,"minecraft:torch":18,"minecraft:dirt":55,"minecraft:anvil":4,"minecraft:stray_spawn_egg":9,"minecraft:skeleton_spawn_egg":5,"minecraft:hopper":102,"minecraft:jungle_trapdoor":1,"minecraft:stone_stairs":37,"minecraft:cobblestone_wall":1,"minecraft:jungle_slab":1,"minecraft:granite":4,"minecraft:spruce_fence":12,"minecraft:stripped_spruce_log":10,"minecraft:polished_blackstone_slab":6,"minecraft:glass":55,"minecraft:wooden_axe":6,"minecraft:stripped_dark_oak_wood":3,"minecraft:bricks":1,"minecraft:bookshelf":5,"minecraft:villager_spawn_egg":1,"minecraft:lantern":13,"minecraft:grass_block":410,"minecraft:slime_block":3,"minecraft:warped_fence":2,"minecraft:smooth_sandstone":1,"minecraft:dark_oak_leaves":6,"minecraft:dark_oak_wood":1,"minecraft:smooth_quartz":149,"minecraft:dark_oak_button":1,"minecraft:item_frame":18,"minecraft:bedrock":14,"minecraft:repeater":516,"minecraft:glowstone":255,"minecraft:redstone_lamp":3,"minecraft:gray_glazed_terracotta":1,"minecraft:black_stained_glass":1,"minecraft:scaffolding":17,"minecraft:hay_block":30,"minecraft:written_book":1,"minecraft:iron_trapdoor":2,"minecraft:minecart":4,"minecraft:stone_pressure_plate":13,"minecraft:observer":34,"minecraft:turtle_egg":52,"minecraft:stripped_spruce_wood":18,"minecraft:water_bucket":28,"minecraft:mossy_stone_bricks":4,"minecraft:wheat_seeds":29,"minecraft:diorite":9,"minecraft:end_rod":223,"minecraft:cobblestone_stairs":3,"minecraft:brick_wall":10,"minecraft:dropper":27,"minecraft:witch_spawn_egg":20,"minecraft:birch_leaves":5,"minecraft:acacia_trapdoor":9,"minecraft:blue_wool":1,"minecraft:purple_glazed_terracotta":3,"minecraft:redstone_block":70,"minecraft:cobblestone_slab":7,"minecraft:vindicator_spawn_egg":2,"minecraft:smooth_quartz_stairs":8,"minecraft:oak_leaves":7,"minecraft:white_wool":26,"minecraft:sand":72,"minecraft:rail":20,"minecraft:comparator":29,"minecraft:vine":8,"minecraft:light_blue_concrete":103,"minecraft:tnt":77,"minecraft:birch_sign":16,"minecraft:note_block":6,"minecraft:painting":14,"minecraft:creeper_spawn_egg":3,"minecraft:sticky_piston":64,"minecraft:redstone_torch":142,"minecraft:oak_log":2,"minecraft:piston":7,"minecraft:lever":30,"minecraft:black_concrete":18,"minecraft:firework_rocket":1,"minecraft:command_block":125,"minecraft:birch_slab":1,"minecraft:brown_wool":1,"minecraft:barrier":381,"minecraft:stone_button":3,"minecraft:netherite_axe":44,"minecraft:stone_slab":1119,"minecraft:red_terracotta":1,"minecraft:spruce_trapdoor":12,"minecraft:gravel":1,"minecraft:yellow_wool":31,"minecraft:coal_block":2,"minecraft:wooden_sword":6,"minecraft:cobblestone":4,"minecraft:acacia_pressure_plate":1,"minecraft:stripped_oak_wood":32,"minecraft:andesite":21,"minecraft:jungle_door":2,"minecraft:lapis_block":8,"minecraft:chain":7,"minecraft:chain_command_block":1,"minecraft:smooth_stone_slab":22,"minecraft:polished_blackstone_button":6,"minecraft:end_portal_frame":28,"minecraft:white_concrete":2,"minecraft:coarse_dirt":1,"minecraft:gray_wool":9},"minecraft:killed":{"minecraft:giant":1,"minecraft:vindicator":3,"minecraft:skeleton":2,"minecraft:chicken":38,"minecraft:drowned":1,"minecraft:skeleton_horse":1,"minecraft:ravager":2,"minecraft:creeper":4,"minecraft:sheep":1,"minecraft:zombie":2,"minecraft:stray":1,"minecraft:villager":7},"minecraft:picked_up":{"minecraft:wooden_axe":4,"minecraft:spruce_leaves":3,"minecraft:iron_chestplate":2,"minecraft:coarse_dirt":2,"minecraft:wheat":71,"minecraft:redstone_block":2,"minecraft:chicken":150,"minecraft:anvil":1,"minecraft:yellow_wool":13,"minecraft:stone_slab":5,"minecraft:birch_button":2,"minecraft:shield":1,"minecraft:stray_spawn_egg":1,"minecraft:stone_stairs":1,"minecraft:wooden_sword":2,"minecraft:sticky_piston":1,"minecraft:snow":1,"minecraft:iron_leggings":3,"minecraft:item_frame":17,"minecraft:armor_stand":1,"minecraft:comparator":5,"minecraft:netherite_sword":2,"minecraft:beef":37,"minecraft:lectern":4,"minecraft:cobblestone_slab":1,"minecraft:redstone_torch":51,"minecraft:written_book":3,"minecraft:player_head":7,"minecraft:poppy":3,"minecraft:smooth_quartz":18,"minecraft:light_gray_wool":1,"minecraft:chest":1,"minecraft:iron_boots":3,"minecraft:egg":1,"minecraft:tipped_arrow":1,"minecraft:black_stained_glass":3,"minecraft:stone":9,"minecraft:birch_trapdoor":1,"minecraft:torch":5,"minecraft:farmland":7,"minecraft:porkchop":175,"minecraft:stone_button":2,"minecraft:diorite":4,"minecraft:music_disc_pigstep":1,"minecraft:vine":1,"minecraft:redstone":735,"minecraft:stone_pressure_plate":1,"minecraft:arrow":4,"minecraft:command_block":7,"minecraft:rotten_flesh":34,"minecraft:hay_block":3,"minecraft:saddle":2,"minecraft:end_rod":2,"minecraft:mutton":28,"minecraft:cobblestone":2,"minecraft:nautilus_shell":1,"minecraft:birch_leaves":1,"minecraft:barrier":5,"minecraft:cooked_beef":122,"minecraft:feather":25,"minecraft:dark_oak_button":1,"minecraft:repeater":69,"minecraft:andesite":2,"minecraft:music_disc_stal":1,"minecraft:filled_map":12,"minecraft:bedrock":1,"minecraft:stripped_spruce_wood":1,"minecraft:gunpowder":2,"minecraft:cobblestone_stairs":1,"minecraft:dirt":20,"minecraft:paper":1,"minecraft:zombie_horse_spawn_egg":4,"minecraft:bone":5,"minecraft:light_blue_banner":7,"minecraft:wheat_seeds":264,"minecraft:iron_sword":1,"minecraft:vindicator_spawn_egg":4,"minecraft:scaffolding":12,"minecraft:gravel":35,"minecraft:dropper":107,"minecraft:sand":19,"minecraft:stripped_spruce_log":1,"minecraft:grass_block":3,"minecraft:coal_ore":1,"minecraft:black_concrete":24,"minecraft:writable_book":8,"minecraft:soul_lantern":2,"minecraft:lever":9,"minecraft:polished_blackstone_button":4,"minecraft:iron_helmet":2,"minecraft:painting":6,"minecraft:birch_sign":4,"minecraft:spruce_sign":4,"minecraft:emerald":6,"minecraft:oak_sapling":1,"minecraft:hopper":18}},"DataVersion":2586}